clever_config/__init__.py
clever_config/_files_loader.py
clever_config/actions.py
clever_config/dict_traversal.py
clever_config/smart_config.py
clever_config/utils.py
clever_config-0.3.0.dist-info/WHEEL
clever_config-0.3.0.dist-info/METADATA
clever_config-0.3.0.dist-info/RECORD
